fastchain/__init__.py
fastchain/_annotations.py
fastchain/chain.py
fastchain/elements.py
fastchain/py.typed
fastchain/reporter.py
fastchain/tools.py
fastchain/wrapper.py
fastchain-1.0.1.dist-info/LICENSE
fastchain-1.0.1.dist-info/METADATA
fastchain-1.0.1.dist-info/WHEEL
fastchain-1.0.1.dist-info/top_level.txt
fastchain-1.0.1.dist-info/RECORD
