Metadata-Version: 2.1
Name: fastchain
Version: 1.0.1
Summary: tool for chain functions easily and safely
Home-page: https://github.com/mediadnan/fastchain
Author: MARSO Adnan
Author-email: mediadnan@gmail.com
Maintainer: MARSO Adnan
License: MIT
Project-URL: bug-tracker, https://github.com/mediadnan/fastchain/issues
Keywords: chain,function,pipe,flow,processing
Classifier: Intended Audience :: Developers
Classifier: Intended Audience :: Science/Research
Classifier: Intended Audience :: Information Technology
Classifier: Operating System :: OS Independent
Classifier: Programming Language :: Python :: 3
Classifier: Programming Language :: Python :: 3 :: Only
Classifier: Programming Language :: Python :: 3.8
Classifier: Programming Language :: Python :: 3.9
Classifier: Programming Language :: Python :: 3.10
Classifier: Topic :: Scientific/Engineering
Classifier: Topic :: Software Development
Classifier: Topic :: Utilities
Classifier: Typing :: Typed
Requires-Python: >=3.8
License-File: LICENSE
Provides-Extra: testing
Requires-Dist: mypy (==0.960) ; extra == 'testing'
Requires-Dist: mypy-extensions (==0.4.3) ; extra == 'testing'
Requires-Dist: pytest (==7.1.2) ; extra == 'testing'
Requires-Dist: pytest-cov (==3.0.0) ; extra == 'testing'
